MANIFEST.in
setup.py
pantograph/__init__.py
pantograph/application.py
pantograph/handlers.py
pantograph/shapes.py
pantograph.egg-info/PKG-INFO
pantograph.egg-info/SOURCES.txt
pantograph.egg-info/dependency_links.txt
pantograph.egg-info/requires.txt
pantograph.egg-info/top_level.txt
pantograph/js/__init__.py
pantograph/js/pantograph.js
pantograph/templates/__init__.py
pantograph/templates/index.html