Metadata-Version: 1.0
Name: pantograph
Version: 0.1.0
Summary: Python library for drawing on HTML5 canvas
Home-page: https://github.com/adicu/pantograph
Author: Howard Mao
Author-email: zhehao.mao@gmail.com
License: MIT
Platform: UNKNOWN
